kgtool/__init__.py
kgtool/core.py
kgtool/kg.py
kgtool/table.py
kgtool-0.0.2.dist-info/DESCRIPTION.rst
kgtool-0.0.2.dist-info/METADATA
kgtool-0.0.2.dist-info/RECORD
kgtool-0.0.2.dist-info/WHEEL
kgtool-0.0.2.dist-info/metadata.json
kgtool-0.0.2.dist-info/top_level.txt
